npmenv.py
npmenv-0.2.0.dist-info/METADATA
npmenv-0.2.0.dist-info/RECORD
npmenv-0.2.0.dist-info/WHEEL
npmenv-0.2.0.dist-info/entry_points.txt
npmenv-0.2.0.dist-info/top_level.txt
