Metadata-Version: 2.1
Name: npmenv
Version: 0.2.0
Summary: A wrapper for npm that stores node_modules outside of project and provides easy access to them.
Home-page: https://github.com/shadow-light/npmenv
Author: shadow-light
Author-email: 42055707+shadow-light@users.noreply.github.com
License: MIT
Platform: UNKNOWN
Requires-Python: ~=3.6
Requires-Dist: appdirs (==1.*,>=1.4.3)
